pypowerschool/__init__.py
pypowerschool/endpoints.py
pypowerschool/powerschool.py
pypowerschool-0.2.0.dist-info/METADATA
pypowerschool-0.2.0.dist-info/WHEEL
pypowerschool-0.2.0.dist-info/licenses/LICENSE
pypowerschool-0.2.0.dist-info/RECORD
