Metadata-Version: 2.1
Name: pypowerschool
Version: 0.2.0
Summary: Synchronous client for PowerSchool API
Project-URL: Homepage, https://github.com/dougpenny/PyPowerSchool
Project-URL: Bug Tracker, https://github.com/dougpenny/PyPowerSchool/issues
Author-email: Doug Penny <dpenny@icloud.com>
License: The MIT License (MIT)
License-File: LICENSE
Classifier: License :: OSI Approved :: MIT License
Classifier: Operating System :: OS Independent
Classifier: Programming Language :: Python :: 3
Classifier: Programming Language :: Python :: 3 :: Only
Classifier: Programming Language :: Python :: 3.8
Classifier: Programming Language :: Python :: 3.9
Classifier: Programming Language :: Python :: 3.10
Classifier: Programming Language :: Python :: 3.11
Requires-Dist: httpx>=0.22.0
